aiopcli/__init__.py
aiopcli/artifacts.py
aiopcli/cli.py
aiopcli/client.py
aiopcli/constants.py
aiopcli/custom_image.py
aiopcli/settings.py
aiopcli/utils.py
aiopcli/commands/deploy.py
aiopcli/commands/env.py
aiopcli/commands/flows.py
aiopcli/commands/image.py
aiopcli/commands/published.py
aiopcli/commands/schedule.py
aiopcli/commands/servable.py
aiopcli-1.3.0.dist-info/entry_points.txt
aiopcli-1.3.0.dist-info/WHEEL
aiopcli-1.3.0.dist-info/METADATA
aiopcli-1.3.0.dist-info/RECORD
