Metadata-Version: 2.1
Name: aiopcli
Version: 1.3.0
Summary: aiopcli
Author-email: Charles Melby-Thompson <charles.thompson@inside.ai>, Kazutoshi Arimoto <kazutoshi.a@inside.ai>
Requires-Python: >=3.8
Classifier: Programming Language :: Python :: 3
Classifier: License :: OSI Approved :: Apache Software License
Classifier: Operating System :: OS Independent
Requires-Dist: atomicwrites
Requires-Dist: click
Requires-Dist: httpx
Requires-Dist: pydantic
Requires-Dist: toml
Requires-Dist: fastapi ; extra == "dev"
Requires-Dist: pre-commit ; extra == "dev"
Requires-Dist: pytest ; extra == "dev"
Requires-Dist: pytest-httpx ; extra == "dev"
Requires-Dist: tenacity ; extra == "dev"
Requires-Dist: uvicorn ; extra == "dev"
Provides-Extra: dev
